{
  "TRANSPORTS.DRONES.RESTRICTIONS$WMTS": {
    "0": {
      "title": "@limite",
      "subtitle": "Restrictions UAS catégorie Ouverte et Aéromodélisme - Source : SIA",
      "bodyBefore": [
        ["* Sauf conditions particulières publiées à l'arrêté « espaces » du 3 décembre 2020"]
      ]
    }
  },
  "VILLAGESETAPE$WMS": {
    "0": {
      "title": "@toponyme",
      "subtitle": "Village étapes - Source : Fédération française des villages étapes",
      "bodyAfter": [
        ["<p class=\"positionWeb positionInfo\"><a href=https://www.village-etape.fr/les-villages-etapes/ target=\"_blank\">Accéder au site web</a></p>"]
      ]
    }
  },
  "POI.MUSEUM$WMS": {
    "0": {
      "title": "@toponyme",
      "subtitle": "Musées - Source : IGN",
      "bodyAfter": [
        ["<p class=\"positionWeb positionInfo\"><a href=http://www.culture.gouv.fr/public/mistral/museo_fr?ACTION=CHERCHER&FIELD_98=REF&VALUE_98={{identifiant_gestionnaire}} target=\"_blank\">Accéder à la fiche Muséofile</a></p>"]
      ]
    }
  },
  "CJP-PARCS-JARDINS_BDD-POI_WLD_WM$WMS": {
    "0": {
      "title": "@name",
      "subtitle": "Parcs et Jardins - Source : Conservatoire des jardins et paysages",
      "bodyBefore": [
        ["{{cjp}}"]
      ],
      "bodyAfter": [
        ["<p class=\"positionWeb positionInfo\"><a href=\"{{url}}\"",  "alt=\"{{url}}\" target=\"_blank\">", "Accéder à la fiche</a></p>"]
      ]
    }
  },
  "POI.MONUMENTS_BDD_WLD_WM$WMS": {
    "0": {
      "title": "@name",
      "subtitle": "Monuments nationaux - Source : Centre des monuments nationaux",
      "bodyAfter": [
        ["<img src=\"https://data.geopf.fr/annexes/ressources/poicmn/{{image}}\">"],
        ["<p class=\"monumentsHistoriquesImageAuthor\">{{image_author}}</p>"],
        ["<p class=\"monumentsHistoriquesContent\">{{content}}</p>"]
      ]
    }
  },
  "IGNF_SITES-UNESCO$WMS": {

    "0": {
      "title": "@nom",
      "title2": "@sous_titre",
      "subtitle": "Sites du patrimoine mondial de l'UNESCO - Sources : UNESCO, IGN",
      "bodyAfter": [
        ["<p class=\"unescoDate\"><img class=\"unescoimg\" src=\"https://data.geopf.fr/annexes/ressources/UNESCO/Unesco-Images-Redimentionnees/{{nom_image}}\">"],
        ["Année d'inscription : {{date_inscription}}</p>"],
        ["<p class=\"monumentsHistoriquesContent\">{{description}}</p>"],
        ["<p class=\"positionWeb positionInfo\"><a target=\"_blank\" href=\"{{lien_unesco}}\">Accéder à la fiche UNESCO</a></p>"]
      ]
    }
  },
  "Patrinat_ZPS$WMTS": {
    "0": {
      "title": "@nom_site",
      "subtitle": "Sites NATURA 2000 au titre de la Directive Oiseaux - Source : Inventaire National du Patrimoine Naturel (INPN), Ministère de la Transition écologique, Muséum national d’Histoire naturelle (MNHN)",
      "bodyAfter": [
        ["<p class=\"positionWeb positionInfo\"><a href=\"{{url_fiche}}\" target=\"_blank\">Accéder à la fiche</a></p>"]
      ]
    }
  },
  "Patrinat_SIC$WMTS": {
    "0": {
      "title": "@nom_site",
      "subtitle": "Sites Natura 2000 au titre de la Directive Habitats - Source : Inventaire National du Patrimoine Naturel (INPN), Ministère de la Transition écologique, Muséum national d’Histoire naturelle (MNHN)",
      "bodyBefore": [
      ],
      "bodyAfter": [
        ["<p class=\"positionWeb positionInfo\"><a href=\"{{url_fiche}}\" target=\"_blank\">Accéder à la fiche</a></p>"]
      ]
    }
  },
  "PROTECTEDAREAS.ZPS$WMTS": {
    "0": {
      "title": "@sitename",
      "subtitle": "Sites NATURA 2000 au titre de la Directive Oiseaux - Source : Inventaire National du Patrimoine Naturel (INPN), Ministère de la Transition écologique, Muséum national d’Histoire naturelle (MNHN)",
      "bodyAfter": [
        ["<p class=\"positionWeb positionInfo\"><a href=\"{{url}}\" target=\"_blank\">Accéder à la fiche</a></p>"]
      ]
    }
  },
  "PROTECTEDAREAS.SIC$WMTS": {
    "0": {
      "title": "@sitename",
      "subtitle": "Sites Natura 2000 au titre de la Directive Habitats - Source : Inventaire National du Patrimoine Naturel (INPN), Ministère de la Transition écologique, Muséum national d’Histoire naturelle (MNHN)",
      "bodyBefore": [
      ],
      "bodyAfter": [
        ["<p class=\"positionWeb positionInfo\"><a href=\"{{url}}\" target=\"_blank\">Accéder à la fiche</a></p>"]
      ]
    }
  },
  "PROTECTEDAREAS.PN$WMTS": {
    "0": {
      "title": "@nom",
      "subtitle": "Parcs nationaux - Source : Inventaire National du Patrimoine Naturel (INPN), Parcs Nationaux de France, Muséum national d’Histoire naturelle (MNHN)",
      "bodyAfter": [
        ["<p class=\"positionWeb positionInfo\"><a href=\"{{url}}\" target=\"_blank\">Accéder à la fiche</a></p>"]
      ]
    }
  },
  "PROTECTEDAREAS.PNR$WMTS": {
    "0": {
      "title": "@nom",
      "subtitle": "Parcs naturels régionaux - Source : Inventaire National du Patrimoine Naturel (INPN), Fédération des Parcs naturels régionaux de France, Muséum national d’Histoire naturelle (MNHN)",
      "bodyAfter": [
        ["<p class=\"positionWeb positionInfo\"><a href=\"{{url}}\" target=\"_blank\">Accéder à la fiche</a></p>"]
      ]
    }
  },
  "PROTECTEDAREAS.RN$WMTS": {
    "0": {
      "title": "@nom",
      "subtitle": "Réserves naturelles nationales - Source : Inventaire National du Patrimoine Naturel (INPN), Réserves naturelles de France (RNF), Muséum national d’Histoire naturelle (MNHN)",
      "bodyAfter": [
        ["<p class=\"positionWeb positionInfo\"><a href=\"{{url}}\" target=\"_blank\">Accéder à la fiche</a></p>"]
      ]
    }
  },
  "PROTECTEDSITES.MNHN.RESERVES-REGIONALES$WMTS": {
    "0": {
      "title": "@nom",
      "subtitle": "Réserves naturelles régionales - Source : Inventaire National du Patrimoine Naturel (INPN), Muséum national d’Histoire naturelle (MNHN)",
      "bodyAfter": [
        ["<p class=\"positionWeb positionInfo\"><a href=\"{{url}}\" target=\"_blank\">Accéder à la fiche</a></p>"]
      ]
    }
  },
  "PROTECTEDAREAS.RNC$WMTS": {
    "0": {
      "title": "@nom",
      "subtitle": "Réserves Naturelles de Corse - Source : Inventaire National du Patrimoine Naturel (INPN), Muséum national d’Histoire naturelle (MNHN)",
      "bodyAfter": [
        ["<p class=\"positionWeb positionInfo\"><a href=\"{{url}}\" target=\"_blank\">Accéder à la fiche</a></p>"]
      ]
    }
  },
  "FORETS.PUBLIQUES$WMTS": {
    "13": {
      "title": "@llib_frt",
      "subtitle": "Forêts publiques - Source : Office National des Forêts"
    },
    "0": {
      "title": "@llib2_frt",
      "subtitle": "Forêts publiques - Source : Office National des Forêts"
    }
  },
  "LANDCOVER.FORESTINVENTORY.V2$WMTS": {
    "0": {
      "title": "@tfv",
      "subtitle": "Carte forestière - Source : IGN",
      "bodyBefore": [
        ["Type générique :", "{{tfv_g11}}"],
        ["Essence :", "{{essence}}"]
      ]
    }
  },
  "CADASTRALPARCELS.PARCELLAIRE_EXPRESS$WMTS":{
    "0": {
      "title": "Parcelles Cadastrales",
      "subtitle": "PCI vecteur - Source : DGFIP",
      "bodyBefore": [
        ["Numéro de parcelle :", "{{numero}}"],
        ["Feuille :", "{{feuille}}"],
        ["Section :", "{{section}}"],
        ["Contenance :", "{{contenance}}"]
      ]
    }
  },
  "LANDUSE.AGRICULTURE2023$WMTS": {
    "0" :{
      "pretitle": "Culture : ",
      "title": "@nom_cultu",
      "subtitle": "Registre parcellaire graphique 2023 - Source : Agence de services et de paiements (ASP)"
    }
  },

  "LIMITES_ADMINISTRATIVES_EXPRESS.LATEST$WMTS": {
    "12": {
      "title": "@nom_officiel",
      "subtitle": "Limites administratives mises à jour en continu - Source : IGN",
      "bodyBefore": [
        ["Commune :", "{{nom_officiel}}"],
        ["Code INSEE :", "{{code_insee}}"],
        ["Statut :", "{{statut}}"],
        ["Département :", "{{code_insee_du_departement}}"],
        ["Population : {{population}} habitants"]
      ],
      "bodyAfter": [
        ["<p class=\"positionWeb positionInfo\"><a target=\"_blank\" href=\"https://www.insee.fr/fr/statistiques/2011101?geo=COM-{{code_insee}}\">Accéder à la fiche INSEE</a></p>", "<p class=\"positionWeb positionInfo\"><a target=\"_blank\" href=\"{{fiche_wikipedia}}\">Accéder à la fiche Wikipédia</a></p>"]
      ]
    },
    "11": {
      "title": "@nom_officiel",
      "subtitle": "Limites administratives mises à jour en continu - Source : IGN",
      "bodyBefore": [
        ["Nature : Canton"]
      ]
    },
    "10": {
      "title": "@nom_officiel",
      "subtitle": "Limites administratives mises à jour en continu - Source : IGN",
      "bodyBefore": [
        ["Nature :", "{{nature}}"]
      ],
      "bodyAfter": [
        ["<p class=\"positionWeb positionInfo\"><a target=\"_blank\" href=\"https://www.insee.fr/fr/statistiques/2011101?geo=EPCI-{{code_siren}}\">Accéder à la fiche INSEE</a></p>"]
      ]
    },
    "9": {
      "title": "@nom_officiel",
      "subtitle": "Limites administratives mises à jour en continu - Source : IGN",
      "bodyBefore": [
        ["Arrondissement Départemental :", "{{nom_officiel}}"]
      ],
      "bodyAfter": [
        ["<p class=\"positionWeb positionInfo\"><a target=\"_blank\" href=\"https://www.insee.fr/fr/statistiques/2011101?geo=ARR-{{code_insee_du_departement}}{{code_insee}}\">Accéder à la fiche INSEE</a></p>"]
      ]
    },
    "7": {
      "title": "@nom_officiel",
      "subtitle": "Limites administratives mises à jour en continu - Source : IGN",
      "bodyBefore": [
        ["Code INSEE :", "{{code_insee}}"]
      ],
      "bodyAfter": [
        ["<p class=\"positionWeb positionInfo\"><a target=\"_blank\" href=\"https://www.insee.fr/fr/statistiques/2011101?geo=DEP-{{code_insee}}\">Accéder à la fiche INSEE</a></p>"]
      ]
    },
    "0": {
      "title": "@nom_officiel",
      "subtitle": "Limites administratives mises à jour en continu - Source : IGN",
      "bodyAfter": [
        ["<p class=\"positionWeb positionInfo\"><a target=\"_blank\" href=\"https://www.insee.fr/fr/statistiques/2011101?geo=REG-{{code_insee}}\">Accéder à la fiche INSEE</a></p>"]
      ]
    }
  }
}
